xapian/__init__.cpython-313.opt-1.pyc
xapian/__init__.cpython-313.pyc
xapian/__init__.py
xapian/_xapian.cpython-313-x86_64-linux-musl.so
xapian_bindings_binary.libs/libuuid-3ed1ebff.so.1.3.0
xapian_bindings_binary.libs/libstdc++-496613c0.so.6.0.32
xapian_bindings_binary.libs/libgcc_s-a3a07607.so.1
xapian_bindings_binary.libs/libxapian-c4d783c3.so.30.13.0
xapian_bindings_binary-1.4.26.dist-info/RECORD
xapian_bindings_binary-1.4.26.dist-info/WHEEL
xapian_bindings_binary-1.4.26.dist-info/top_level.txt
xapian_bindings_binary-1.4.26.dist-info/METADATA
