Metadata-Version: 2.1
Name: xapian-bindings-binary
Version: 1.4.26
Summary: xapian bindings binary builds
Home-page: https://github.com/mayli/xapian-bindings/
Author: xapian-bindings dev
